entomb/__init__.py
entomb/constants.py
entomb/core.py
entomb/exceptions.py
entomb/listing.py
entomb/processing.py
entomb/reporting.py
entomb/utilities.py
tests/__init__.py
tests/constants.py
tests/helpers.py
tests/test_core.py
tests/test_listing.py
tests/test_processing.py
tests/test_reporting.py
tests/test_utilities.py
entomb-0.4.0.dist-info/LICENCE
entomb-0.4.0.dist-info/METADATA
entomb-0.4.0.dist-info/WHEEL
entomb-0.4.0.dist-info/entry_points.txt
entomb-0.4.0.dist-info/top_level.txt
entomb-0.4.0.dist-info/RECORD
