Metadata-Version: 2.1
Name: entomb
Version: 0.4.0
Summary: File immutability manager
Home-page: https://github.com/countermeasure/entomb
Author: Sky Christensen
Author-email: sky@skychristensen.com
License: MIT
Keywords: immutable
Platform: UNKNOWN
Classifier: Development Status :: 4 - Beta
Classifier: Environment :: Console
Classifier: License :: OSI Approved :: MIT License
Classifier: Operating System :: POSIX :: Linux
Classifier: Programming Language :: Python :: 3
Classifier: Programming Language :: Python :: 3.5
Classifier: Programming Language :: Python :: 3.6
Classifier: Programming Language :: Python :: 3.7
Classifier: Programming Language :: Python :: 3.8
Classifier: Programming Language :: Python :: 3.9
Classifier: Topic :: Utilities
Requires-Python: >=3.5
